giskard/__init__.py
giskard/path_utils.py
giskard/settings.py
giskard/client/dtos.py
giskard/client/io_utils.py
giskard/client/python_utils.py
giskard/core/__init__.py
giskard/core/core.py
giskard/core/dataset_validation.py
giskard/core/errors.py
giskard/core/kwargs_utils.py
giskard/core/model_validation.py
giskard/core/savable.py
giskard/core/suite.py
giskard/core/test_result.py
giskard/core/validation.py
giskard/datasets/__init__.py
giskard/datasets/base/__init__.py
giskard/datasets/metadata/__init__.py
giskard/datasets/metadata/indexing.py
giskard/datasets/metadata/registry.py
giskard/datasets/metadata/text_metadata_provider.py
giskard/demo/__init__.py
giskard/demo/linear_regression.py
giskard/demo/llm_ipcc_climate_change.py
giskard/demo/titanic.csv
giskard/demo/titanic_classification.py
giskard/exceptions/IllegalArgumentError.py
giskard/exceptions/__init__.py
giskard/exceptions/giskard_exception.py
giskard/functions/__init__.py
giskard/functions/slicing.py
giskard/functions/transformation.py
giskard/integrations/__init__.py
giskard/integrations/avid.py
giskard/integrations/nemoguardrails.py
giskard/integrations/mlflow/__init__.py
giskard/integrations/mlflow/evaluation_artifacts.py
giskard/integrations/mlflow/giskard_evaluator.py
giskard/integrations/mlflow/giskard_evaluator_utils.py
giskard/integrations/wandb/__init__.py
giskard/integrations/wandb/wandb_utils.py
giskard/llm/__init__.py
giskard/llm/config.py
giskard/llm/errors.py
giskard/llm/testcase.py
giskard/llm/utils.py
giskard/llm/client/__init__.py
giskard/llm/client/base.py
giskard/llm/client/bedrock.py
giskard/llm/client/copilot.py
giskard/llm/client/gemini.py
giskard/llm/client/groq_client.py
giskard/llm/client/litellm.py
giskard/llm/client/logger.py
giskard/llm/client/mistral.py
giskard/llm/client/openai.py
giskard/llm/embeddings/__init__.py
giskard/llm/embeddings/base.py
giskard/llm/embeddings/bedrock.py
giskard/llm/embeddings/fastembed.py
giskard/llm/embeddings/litellm.py
giskard-2.18.0.dist-info/licenses/LICENSE
giskard-2.18.0.dist-info/METADATA
giskard-2.18.0.dist-info/WHEEL
giskard-2.18.0.dist-info/entry_points.txt
giskard-2.18.0.dist-info/top_level.txt
giskard-2.18.0.dist-info/RECORD
