Metadata-Version: 2.4
Name: giskard
Version: 2.18.0
Summary: The testing framework dedicated to ML models, from tabular to LLMs
Author-email: Giskard AI <hello@giskard.ai>
License: Apache Software License 2.0
Project-URL: Homepage, https://giskard.ai
Project-URL: Source Code, https://github.com/Giskard-AI/giskard
Project-URL: Bug Tracker, https://github.com/Giskard-AI/giskard/issues
Project-URL: Documentation, https://docs.giskard.ai/
Project-URL: Discord, https://discord.gg/ABvfpbu69R
Project-URL: Linkedin, https://www.linkedin.com/company/giskard-ai
Project-URL: Mastodon, https://fosstodon.org/@Giskard
Project-URL: Twitter, https://twitter.com/giskard_ai
Keywords: Artificial Intelligence,Machine Learning,Quality,MLOps
Classifier: Development Status :: 4 - Beta
Classifier: Intended Audience :: Developers
Classifier: Intended Audience :: Science/Research
Classifier: Operating System :: OS Independent
Classifier: Topic :: Scientific/Engineering :: Artificial Intelligence
Classifier: License :: OSI Approved :: Apache Software License
Classifier: Programming Language :: Python :: 3.9
Classifier: Programming Language :: Python :: 3.10
Classifier: Programming Language :: Python :: 3.11
Classifier: Programming Language :: Python :: 3.12
Requires-Python: <3.13,>=3.9
License-File: LICENSE
Requires-Dist: cloudpickle>=1.1.1
Requires-Dist: zstandard>=0.10.0
Requires-Dist: mlflow-skinny>=2
Requires-Dist: numpy<2,>=1.26.0
Requires-Dist: scikit-learn>=1.0
Requires-Dist: scipy<1.12.0,>=1.7.3
Requires-Dist: mixpanel>=4.4.0
Requires-Dist: requests>=2.19
Requires-Dist: pydantic<3,>1
Requires-Dist: pandas>=2.0
Requires-Dist: xxhash>=3.2.0
Requires-Dist: langdetect>=1.0.9
Requires-Dist: chardet
Requires-Dist: jinja2>=3
Requires-Dist: requests-toolbelt>=0.9.1
Requires-Dist: setuptools
Requires-Dist: typing_extensions
Requires-Dist: pyyaml
Requires-Dist: packaging
Requires-Dist: markdown
Requires-Dist: colorama
Requires-Dist: num2words>=0.5.13
Requires-Dist: griffe<2.0.0,>=1.0.0
Requires-Dist: ipython
Provides-Extra: llm
Requires-Dist: openai; extra == "llm"
Requires-Dist: evaluate>=0.4.1; extra == "llm"
Requires-Dist: bert-score>=0.3.13; extra == "llm"
Requires-Dist: tenacity>=4.11.0; extra == "llm"
Requires-Dist: faiss-cpu<1.11.0,>=1.7.4; extra == "llm"
Requires-Dist: bokeh<3.5,>=3.3.4; extra == "llm"
Requires-Dist: umap-learn>=0.5.5; extra == "llm"
Requires-Dist: scikit-learn>=1.3.2; extra == "llm"
Requires-Dist: litellm<1.66.0; extra == "llm"
Requires-Dist: groq>=0.10.0; extra == "llm"
Provides-Extra: talk
Requires-Dist: openai; extra == "talk"
Requires-Dist: tenacity>=4.11.0; extra == "talk"
Requires-Dist: shap<0.44.1,>=0.41.0; extra == "talk"
Requires-Dist: tabulate==0.9.0; extra == "talk"
Provides-Extra: tensorflow
Requires-Dist: tensorflow-hub>=0.16.0; (sys_platform != "win32" and platform_system != "Windows") and extra == "tensorflow"
Requires-Dist: tensorflow-macos==2.16.2; (sys_platform == "darwin" and platform_machine == "arm64") and extra == "tensorflow"
Requires-Dist: tensorflow==2.16.2; extra == "tensorflow"
Requires-Dist: tensorflow-text==2.16.1; (python_version < "3.11" and (sys_platform == "linux" or sys_platform == "darwin") and platform_machine == "x86_64") and extra == "tensorflow"
Dynamic: license-file
